chirpier/__init__.py
chirpier/client.py
chirpier/errors.py
chirpier/event.py
chirpier/utils.py
chirpier-0.0.6.dist-info/LICENCE
chirpier-0.0.6.dist-info/METADATA
chirpier-0.0.6.dist-info/WHEEL
chirpier-0.0.6.dist-info/RECORD
