Metadata-Version: 2.1
Name: chirpier
Version: 0.0.6
Summary: A Python SDK for interacting with the Chirpier API.
License: MIT
Author: Chirpier
Author-email: contact@chirpier.co
Requires-Python: >=3.10,<4.0
Classifier: License :: OSI Approved :: MIT License
Classifier: Operating System :: OS Independent
Classifier: Programming Language :: Python :: 3
Classifier: Programming Language :: Python :: 3.10
Classifier: Programming Language :: Python :: 3.11
Classifier: Programming Language :: Python :: 3.12
Classifier: Programming Language :: Python :: 3.13
Requires-Dist: pydantic (>=2.5.2,<3.0.0)
Requires-Dist: requests (>=2.25.1,<3.0.0)
Requires-Dist: retrying (>=1.3.3,<2.0.0)
